environ_secretmanager/__init__.py
environ_secretmanager/env_secrets.py
environ_secretmanager-0.1.4.dist-info/METADATA
environ_secretmanager-0.1.4.dist-info/WHEEL
environ_secretmanager-0.1.4.dist-info/RECORD
