Metadata-Version: 2.3
Name: environ_secretmanager
Version: 0.1.4
Summary: Get secrets from Google Cloud Secret Manager or Environment.
Author: Hareem Adderley
Author-email: hadderley@kingpinapps.com
Requires-Python: >=3.10,<4.0
Classifier: Development Status :: 4 - Beta
Classifier: License :: OSI Approved :: Apache Software License
Classifier: Operating System :: OS Independent
Classifier: Programming Language :: Python :: 3
Classifier: Programming Language :: Python :: 3.10
Classifier: Programming Language :: Python :: 3.11
Classifier: Programming Language :: Python :: 3.12
Classifier: Programming Language :: Python :: 3.13
Requires-Dist: django-environ (>=0.12.0,<0.13.0)
Requires-Dist: google-cloud-secret-manager (>=2.18.0,<3.0.0)
